xts_api_client/__init__.py
xts_api_client/interactive_socket.py
xts_api_client/interactive_socket_client.py
xts_api_client/market_data_socket.py
xts_api_client/market_data_socket_client.py
xts_api_client/py.typed
xts_api_client/xts_connect.py
xts_api_client/xts_connect_async.py
xts_api_client/xts_exception.py
xts_api_client/helper/__init__.py
xts_api_client/helper/helper.py
xts_api_client/helper/helper_classes.py
xts_api_client-0.1.21.dist-info/METADATA
xts_api_client-0.1.21.dist-info/WHEEL
xts_api_client-0.1.21.dist-info/RECORD
