Metadata-Version: 2.4
Name: xts-api-client
Version: 0.1.21
Summary: A Package designed for connecting to a Stock Broker that uses Symphony Fintech Solutions Pvt. Ltd for there API.
Project-URL: Homepage, https://github.com/sharanchetan/xts-api-client
Project-URL: Documentation, https://xts-api-client.readthedocs.io/en/latest/
Author-email: Chetan Sharan <chetan.sharan@rmoneyindia.com>
Requires-Python: >=3.12
Requires-Dist: aiohttp==3.11.11
Requires-Dist: httpx>=0.28.1
Requires-Dist: pandas>=2.2.3
Requires-Dist: pre-commit>=3.7.0
Requires-Dist: python-dotenv>=1.0.1
Requires-Dist: python-socketio-rishavrmoney>=4.6.1
Requires-Dist: requests>=2.32.3
Requires-Dist: urllib3>=2.2.3
